README.rst
setup.py
signxml_sunat/__init__.py
signxml_sunat.egg-info/PKG-INFO
signxml_sunat.egg-info/SOURCES.txt
signxml_sunat.egg-info/dependency_links.txt
signxml_sunat.egg-info/requires.txt
signxml_sunat.egg-info/top_level.txt
test/test.py