Metadata-Version: 1.1
Name: signxml-sunat
Version: 1.0.3
Summary: SUNAT - sign and verify xml
Home-page: https://github.com/danilobrinu/signxml_sunat
Author: @danilobrinu
Author-email: ddbn.c2@gmail.com
License: UNKNOWN
Platform: UNKNOWN
Classifier: License :: OSI Approved :: MIT License
Classifier: Programming Language :: Python
Classifier: Programming Language :: Python :: 3
Classifier: Topic :: Software Development :: Libraries :: Python Modules
